RDS/Informations.py
RDS/ROParser.py
RDS/Service.py
RDS/ServiceException.py
RDS/Token.py
RDS/User.py
RDS/Util.py
RDS/__init__.py
research_data_services_common-0.54.dist-info/LICENSE
research_data_services_common-0.54.dist-info/METADATA
research_data_services_common-0.54.dist-info/WHEEL
research_data_services_common-0.54.dist-info/top_level.txt
research_data_services_common-0.54.dist-info/RECORD
