Metadata-Version: 2.1
Name: research-data-services-common
Version: 0.54
Summary: The token and service implementation  of sciebo RDS
Home-page: https://github.com/Sciebo-RDS/py-research-data-services-common
Author: Peter Heiss
Author-email: peter.heiss@uni-muenster.de
Maintainer: Peter Heiss
Maintainer-email: peter.heiss@uni-muenster.de
License: MIT
Keywords: Datastructure,Service,Research,Data
Classifier: Development Status :: 2 - Pre-Alpha
Classifier: Environment :: Console
Classifier: Intended Audience :: Developers
Classifier: License :: OSI Approved :: MIT License
Classifier: Operating System :: OS Independent
Classifier: Programming Language :: Python
Classifier: Programming Language :: Python :: 3
Classifier: Programming Language :: Python :: 3.6
Classifier: Programming Language :: Python :: 3.7
Classifier: Programming Language :: Python :: 3.8
Classifier: Programming Language :: Python :: Implementation :: CPython
Requires-Python: >=3.6
License-File: LICENSE
Provides-Extra: flask
Requires-Dist: flask ; extra == 'flask'
